{
	"instance" : {
		"hostname" : "us 2/24/2009 14:40",
		"map:to:" : "us 2/24/2009 14:37",
		"initialize" : "us 2/24/2009 15:51",
		"server" : "us 2/24/2009 15:53",
		"printHeaderFor:on:" : "us 2/24/2009 15:24",
		"configureFromDictionary:" : "us 2/24/2009 16:32",
		"printMessageFor:on:" : "us 2/24/2009 15:24",
		"priorityFor:" : "us 2/24/2009 14:35",
		"printPriorityFor:on:" : "us 2/24/2009 15:24",
		"addEvent:" : "us 2/24/2009 15:53",
		"unmappedFacility" : "us 2/24/2009 15:46",
		"unmappedFacility:" : "us 2/24/2009 15:46",
		"printTimestampFor:on:" : "us 2/24/2009 15:25",
		"messageFor:" : "us 2/24/2009 15:53",
		"port" : "us 2/24/2009 15:54",
		"printHostnameOn:" : "us 2/24/2009 15:24",
		"hostname:" : "us 2/24/2009 14:40",
		"sendMessage:" : "us 2/24/2009 19:28",
		"severityFor:" : "us 2/24/2009 15:52",
		"server:" : "us 2/24/2009 15:53",
		"facilityFor:" : "us 2/24/2009 15:46",
		"port:" : "us 2/24/2009 15:54"
	},
	"class" : {
		"defaultMapping" : "us 2/24/2009 15:49",
		"configureFromDictionary:" : "us 2/24/2009 16:25",
		"defaultHostname" : "us 2/24/2009 15:48",
		"mappingKey" : "us 2/24/2009 15:32",
		"defaultUnmappedFacility" : "us 2/24/2009 15:47",
		"defaultServer" : "us 2/24/2009 15:48",
		"defaultLogName" : "us 2/24/2009 15:32",
		"defaultPort" : "us 2/24/2009 15:48",
		"iniFileFields" : "us 2/24/2009 15:43"
	}
}